netmiko_mhrt/__init__.py
netmiko_mhrt-1.0.6.dist-info/LICENSE
netmiko_mhrt-1.0.6.dist-info/METADATA
netmiko_mhrt-1.0.6.dist-info/WHEEL
netmiko_mhrt-1.0.6.dist-info/top_level.txt
netmiko_mhrt-1.0.6.dist-info/RECORD
