Metadata-Version: 2.1
Name: netmiko_mhrt
Version: 1.0.6
Summary: a forked version of netmiko_multihop
Home-page: https://github.com/1mmortalPhoenix/netmiko_mhrt
Author: Felix Li
Author-email: immphoenix@gmail.com
License: ASL V2
Classifier: License :: OSI Approved :: Apache Software License
Classifier: Programming Language :: Python :: 3.7
Classifier: Programming Language :: Python :: 3.8
Classifier: Topic :: System :: Installation/Setup
Classifier: Topic :: System :: Systems Administration
Classifier: Topic :: Utilities
Requires-Python: >=3.7
License-File: LICENSE
Requires-Dist: netmiko >=4.1.2
